docs/conf.py
docs/history.rst
docs/index.rst
jaraco/net/__init__.py
jaraco/net/dns.py
jaraco/net/dnsbl.py
jaraco/net/icmp.py
jaraco/net/importer.py
jaraco/net/inet.py
jaraco/net/ntp.py
jaraco/net/ping-isp.py
jaraco/net/rss.py
jaraco/net/scanner.py
jaraco/net/site.py
jaraco/net/stats.py
jaraco/net/tail.py
jaraco/net/tcp.py
jaraco/net/udp.py
jaraco/net/wake.py
jaraco/net/devices/__init__.py
jaraco/net/devices/base.py
jaraco/net/devices/darwin.py
jaraco/net/devices/linux.py
jaraco/net/devices/win32.py
jaraco/net/http/__init__.py
jaraco/net/http/caching.py
jaraco/net/http/content.py
jaraco/net/http/cookies.py
jaraco/net/http/htmldir.py
jaraco/net/http/servers.py
jaraco/net/http/static.py
jaraco/net/http/staticdirindex.py
jaraco/net/pinger/pinger.conf
tests/nic.bo.html
tests/test_cookies.py
tests/test_importer.py
tests/http/test_caching.py
jaraco.net-10.2.2.dist-info/LICENSE
jaraco.net-10.2.2.dist-info/METADATA
jaraco.net-10.2.2.dist-info/WHEEL
jaraco.net-10.2.2.dist-info/entry_points.txt
jaraco.net-10.2.2.dist-info/top_level.txt
jaraco.net-10.2.2.dist-info/RECORD
